tkrdevtest/__init__.py
tkrdevtest/__main__.py
tkrdevtest-0.0.1.dist-info/LICENSE
tkrdevtest-0.0.1.dist-info/METADATA
tkrdevtest-0.0.1.dist-info/WHEEL
tkrdevtest-0.0.1.dist-info/entry_points.txt
tkrdevtest-0.0.1.dist-info/top_level.txt
tkrdevtest-0.0.1.dist-info/RECORD
