Metadata-Version: 2.1
Name: tkrdevtest
Version: 0.0.1
Summary: Testing toolkitr.
Home-page: https://github.com/toolkitr/tkrdisc
Author: tkr.
Author-email: toolkitr.email@gmail.com
Classifier: Programming Language :: Python :: 3.10
Classifier: Programming Language :: Python :: 3.11
Classifier: License :: OSI Approved :: MIT License
Classifier: Development Status :: 3 - Alpha
Classifier: Intended Audience :: Developers
Classifier: Topic :: Software Development :: Build Tools
Requires-Python: >=3.10,<3.12
License-File: LICENSE
